space/__init__.py
space/assets.py
space/commands.py
space/console_queries.py
space/constants.py
space/errors.py
space/gems.py
space/links.py
space/native_procedures.py
space/parameters.py
space/procedure_engines.py
space/procedures.py
space/shell.py
space/silent_queries.py
space/space_pythons.py
space/space_queries.py
space/system.py
space/times.py
space_python-1.2.0.dist-info/METADATA
space_python-1.2.0.dist-info/WHEEL
space_python-1.2.0.dist-info/licenses/LICENSE
space_python-1.2.0.dist-info/RECORD
