Metadata-Version: 2.4
Name: space-python
Version: 1.2.0
Summary: SpacePython core interface
Project-URL: Homepage, https://www.omg.org/solm/
Project-URL: Issues, https://issues.omg.org
Author-email: Object Management Group <space@omg.org>
License: Object Management Group RF-Limited License 
License-File: LICENSE
Classifier: Operating System :: OS Independent
Classifier: Programming Language :: Python :: 3
Requires-Python: >=3.6
